fnv128a/__init__.py
fnv128a-0.0.2.dist-info/LICENSE
fnv128a-0.0.2.dist-info/METADATA
fnv128a-0.0.2.dist-info/WHEEL
fnv128a-0.0.2.dist-info/top_level.txt
fnv128a-0.0.2.dist-info/RECORD
