Metadata-Version: 2.1
Name: fnv128a
Version: 0.0.2
Summary: Python implementation of Golang's fnv128a in hash/fnv
Author-email: Simon Haxby <simon.haxby@gmail.com>
Project-URL: Bug Tracker, https://github.com/avicennax/fnv128a/issues
Project-URL: Homepage, https://github.com/avicennax/fnv128a
Classifier: Programming Language :: Python :: 3
Classifier: License :: OSI Approved :: MIT License
Classifier: Operating System :: OS Independent
Requires-Python: >=3.5
License-File: LICENSE
